reflective/__init__.py
reflective/cache.py
reflective/context.py
reflective/core.py
reflective/core_legacy.py
reflective/exceptions.py
reflective/query.py
reflective/util.py
reflective/types/__init__.py
reflective/types/base.py
reflective/types/dict.py
reflective/types/list.py
reflective/types/numeric.py
reflective/types/simple.py
reflective/types/string.py
reflective/types/tuple.py
tests/test_access.py
tests/test_bools.py
tests/test_delete.py
tests/test_dumps.py
tests/test_dynamic_references.py
tests/test_module_query.py
tests/test_path_queries.py
tests/test_representations.py
tests/test_strings.py
tests/test_typing.py
tests/test_update.py
reflective-0.2.1.dist-info/LICENSE
reflective-0.2.1.dist-info/METADATA
reflective-0.2.1.dist-info/WHEEL
reflective-0.2.1.dist-info/top_level.txt
reflective-0.2.1.dist-info/RECORD
