Metadata-Version: 2.1
Name: reflective
Version: 0.2.1
Summary: Reflective provides a plethora of ways to access and manipulate structured data.
Author-email: Azorian Solutions <help@azorian.solutions>
License: MIT License
Project-URL: Homepage, https://github.com/AzorianSolutions/reflective
Project-URL: Bug Tracker, https://github.com/AzorianSolutions/reflective/issues
Classifier: Programming Language :: Python :: 3
Classifier: License :: OSI Approved :: MIT License
Classifier: Operating System :: OS Independent
Requires-Python: >=3.8
License-File: LICENSE
